Metadata-Version: 2.1
Name: PythonArpitha
Version: 0.0.1
Summary: this is a trial package used for calculation.
Home-page: 
Author: Arpitha SP
Author-email: arpitha06da@gmail.com
License: MIT
License-File: LICENCE.txt
